lid_search/__init__.py
lid_search/__main__.py
lid_search/cli.py
lid_search/lid_search.py
lid_search-0.2.0.dist-info/LICENSE
lid_search-0.2.0.dist-info/METADATA
lid_search-0.2.0.dist-info/WHEEL
lid_search-0.2.0.dist-info/RECORD
