Metadata-Version: 2.3
Name: lid-search
Version: 0.2.0
Summary: Search in the lid database and return the new version number
Author: Romolo Politi
Author-email: romolo.politi@inaf.it
Requires-Python: >=3.7,<3.15
Classifier: Programming Language :: Python :: 3
Classifier: Programming Language :: Python :: 3.11
Classifier: Programming Language :: Python :: 3.12
Classifier: Programming Language :: Python :: 3.13
Requires-Dist: semantic-version-tools (>=1.3.1,<2.0.0)
Requires-Dist: setuptools (>=78.1.1)
